{
  "schema_version": "internal_alpha_manifest_v1",
  "channel": "internal_alpha",
  "latest_version": "0.0.19-alpha.0",
  "latest_version_code": 19,
  "minimum_supported_version": "0.0.13-alpha.0",
  "minimum_supported_version_code": 13,
  "released_at": "2026-06-09T22:09:57Z",
  "requires_save_reset": false,
  "portal_url": "https://draxos-mobile-internal-alpha.pages.dev/",
  "notes": [
    "Bosque Overlay Interaction Authority v1 publicado na URL principal de Internal Alpha.",
    "APK Android, PC ZIP e Web compartilham o mesmo backend remoto.",
    "Bosque permanece vivo e visivel enquanto Arena, Refugio/Base, Loja, Social e Perfil abrem como overlay.",
    "Voltar, Fechar e Esc/Web usam a mesma autoridade de fechamento do overlay e devolvem input ao mesmo node do Bosque sem rebootstrap.",
    "Menus abertos pelo Bosque usam rota de overlay sem acao mutante fantasma.",
    "Refresh read-only nao bloqueia fechamento; respostas tardias sao ignoradas quando o overlay fecha ou muda de rota.",
    "Arena PVE roda dentro do overlay e bloqueia fechamento apenas durante replay ou mutacao critica explicita.",
    "Arena PVE agora exporta e exibe HP/Mana iniciais buffados no replay da proxima luta.",
    "Openworld/Bosque usa operations v2 com ACK obrigatorio e retry local.",
    "Nodes coletaveis mantem cooldown por item via node_state.next_spawn_at e rejeicoes terminais nao ficam presas na fila.",
    "Coleta ativa nao reinicia por movimento leve e ACKs nao fazem rollback visual da mesma sessao.",
    "Menu usa busy por escopo para nao congelar acoes independentes durante requisicoes pendentes.",
    "Fogueira Estavel I so libera receitas apos ACK de structures.fogueira_estavel_1.",
    "Portal/Web rodam no Cloudflare Pages; downloads usam login alpha e URLs assinadas temporarias.",
    "Manifesto recomenda build 0.0.19-alpha.0 e mantem build minima 0.0.13-alpha.0.",
    "Progression Lab usa save separado e nao pontua ranking."
  ],
  "artifacts": {
    "android": {
      "label": "Android APK",
      "url": "https://armxgipvnbbshzqawklw.supabase.co/functions/v1/release/download?artifact=android",
      "sha256": "acffb52c8ff149b215e86de0e713603018b97ec6b9cd06cea530caa58b1e1f7c",
      "auth_required": true
    },
    "pc_windows": {
      "label": "PC Windows ZIP",
      "url": "https://armxgipvnbbshzqawklw.supabase.co/functions/v1/release/download?artifact=pc_windows",
      "sha256": "72110533a1096a39b53efe55129f066032dc43ad58e5b6e5cbca27556756a34b",
      "auth_required": true
    },
    "web": {
      "label": "Web",
      "url": "https://draxos-mobile-internal-alpha.pages.dev/web/index.html"
    }
  },
  "known_issues": [
    "Layout Android paisagem ainda precisa de ergonomia real no aparelho.",
    "APK desta publicacao usa debug_fallback enquanto a keystore release dedicada nao estiver configurada.",
    "Web usa hospedagem hibrida Cloudflare Pages + Supabase Storage; validar / e /web/index.html apos cada deploy.",
    "Dominio estavel do Cloudflare Pages pode exigir Cloudflare Access; validacao publica anonima deve usar preview liberado ou sessao autenticada."
  ]
}
